{
  "welcome": "مرحباً بعودتك",
  "request_cancelled": "تم إلغاء الطلب إلى الخادم",
  "connection_time_out": "أنتهت مهلة الأتصال بالخادم",
  "receive_time_out": "أنتهت مهلة الأستقبال من الخادم",
  "send_time_out": "أنتهت مهلة الأرسال إلي الخادم",
  "internet_connection_error": "فشل الأتصال بالخادم بسبب الإنترنت",
  "unexpected_error": "حدث خطأ غير متوقع",
  "unknown_error": "فشل الأتصال بالخادم  بسبب خطأ غير معروف",
  "bad_certificates_error": "فشل الاتصال بالخادم بسبب شهادة سيئة",
  "email_is_required": "البريد الإلكتروني مطلوب",
  "invalid_email_address": "عنوان البريد الإلكتروني غير صحيح",
  "invalid_phone_number": "رقم الجوال غير صحيح",
  "password_is_required": "كلمة المرور مطلوبة",
  "password_chars_is_not_valid": "أقل عدد من الأحرف هو 8",
  "confirm_password_required": "تأكيد كلمة المرور مطلوب",
  "confirm_password_not_matched": "تأكيد كلمة المرور غير متطابق",
  "first_name_required": "الأسم الأول مطلوب",
  "last_name_required": "الأسم الثاني مطلوب",
  "no_connection": "لا يوجد اتصال بالانترنت، برجاء التحقق من الانترنت و إعادة المحاولة",
  "connected": "متصل بالانترنت",
  "email_taken": "عنوان البريد الإلكتروني مُستخدم من قبل",
  "acc_not_exist": "هذا الحساب غير موجود",
  "credentials_wrong": "خطأ في البيانات",
  "en": "الأنجليزية",
  "ar": "العربية",
  "login": "تسجيل الدخول",
  "logout": "تسجيل الخروج",
  "register": "انشاء حساب جديد",
  "email": "البريد الإلكتروني",
  "password": "كلمة المرور",
  "forget_password": "هل نسيت كلمة المرور؟",
  "don't_have_account": "ليس لديك حساب؟ ",
  "have_account": "لديك حساب؟ ",
  "confirm_password": "تأكيد كلمة المرور",
  "first_name": "الأسم الأول",
  "last_name": "الأسم الثاني",
  "continue": "أكمل",
  "cancel": "إلغاء",
  "confirm": "تأكيد",
  "profile": "الملف الشخصي",
  "language": "اللغة",
  "logout_successful": "تم تسجيل الخروج بنجاح",
  "no_data": "لم يتم العثور على بيانات",
  "try_again": "إعادة المحاولة",
  "account_created_success": "تم إنشاء حسابك بنجاح",
  "see_all": "مشاهدة الكل",
  "auth_error": "خطأ في التسجيل: ",
  "invalid_email_error": "عنوان البريد الإلكتروني غير صالح.",
  "user_disabled_error": "تم تعطيل حساب المستخدم.",
  "user_not_found_error": "لم يتم العثور على المستخدم.",
  "wrong_password_error": "كلمة مرور خاطئة.",
  "account_exist_error": "هناك حساب بنفس البريد الإلكتروني موجود بالفعل ولكنه مرتبط ببيانات مختلفة.",
  "invalid_credential_error": "البيانات غير صالحة.",
  "credential_in_use_error": "البيانات  مرتبطة بالفعل بمستخدم.",
  "email_in_use_error": "عنوان البريد الإلكتروني مُستخدم من قبل",
  "sync": "مزامنة",
  "sync_success": "نجحت المزامنة",
  "sync_failed": "فشلت المزامنة",
  "clear": "اخلاء",
  "from": "من",
  "to": "إلى",
  "choose": "أختيار",
  "change_password": "تغير كلمة المرور",
  "user_delete_successful": "تم حذف المستخدم بنجاح",
  "password_changed_success": "تم تغير كلمة المرور بنجاح",
  "recent_password": "كلمة المرور الحالية",
  "new_password": "كلمة المرور الجديدة",
  "confirm_new_password": "تأكيد كلمة المرور الجديدة",
  "logo_semantic_label": "هذا هو شعار التطبيق",
  "open_screen_scaffold_semantic_label": "هذه هي الشاشة التي يمكنك من خلالها اختيار تسجيل الدخول أو التسجيل",
  "login_screen_scaffold_semantic_label": "هذه هي الشاشة التي من المفترض أن تدخل فيها بريدك الإلكتروني وكلمة المرور لتسجيل الدخول وإذا لم يكن لديك حساب يمكنك الذهاب إلى شاشة التسجيل وأيضا يمكنك الذهاب إلى شاشة نسيان كلمة المرور إذا نسيت كلمة المرور الخاصة بك",
  "login_with_email_or": "تسجيل الدخول باستخدام البريد الإلكتروني الخاص بك أو",
  "google_button_semantic_label": "تسجيل الدخول باستخدام زر جوجل"
}